<metadata xml:lang="en"><Esri><CreaDate>20190529</CreaDate><CreaTime>09361000</CreaTime><ArcGISFormat>1.0</ArcGISFormat><SyncOnce>TRUE</SyncOnce><ModDate>20190531</ModDate><ModTime>8140000</ModTime><scaleRange><minScale>150000000</minScale><maxScale>5000</maxScale></scaleRange><ArcGISProfile>ItemDescription</ArcGISProfile></Esri><tool name="LandCoverChange" displayname="Calculate land cover accounts" toolboxalias="LUCI" xmlns=""><arcToolboxHelpPath>c:\program files (x86)\arcgis\desktop10.6\Help\gp</arcToolboxHelpPath><parameters><param name="Output_folder" displayname="Output folder" type="Required" direction="Input" datatype="Folder" expression="Output_folder"><dialogReference>&lt;DIV STYLE="text-align:Left;"&gt;&lt;DIV&gt;&lt;P&gt;&lt;SPAN&gt;Specify the path and folder name where output from this tool should be stored.&lt;/SPAN&gt;&lt;/P&gt;&lt;/DIV&gt;&lt;/DIV&gt;</dialogReference></param><param name="Land_cover_option" displayname="Land cover input option" type="Required" direction="Input" datatype="String" expression="One shapefile with multiple fields | Two separate shapefiles or rasters"><dialogReference>&lt;DIV STYLE="text-align:Left;"&gt;&lt;DIV&gt;&lt;P&gt;&lt;SPAN&gt;Two land cover options are available:&lt;/SPAN&gt;&lt;/P&gt;&lt;UL&gt;&lt;LI&gt;&lt;P&gt;&lt;SPAN STYLE="font-style:italic;"&gt;One shapefile with multiple files:&lt;/SPAN&gt;&lt;SPAN&gt; The user can enter one shapefile with two fields specifying land cover from two different timeframes (e.g. 2000 and 2015).&lt;/SPAN&gt;&lt;/P&gt;&lt;/LI&gt;&lt;LI&gt;&lt;P&gt;&lt;SPAN STYLE="font-style:italic;"&gt;Two separate shapefiles:&lt;/SPAN&gt;&lt;SPAN&gt; The user can enter two shapefiles with one land cover field each.&lt;/SPAN&gt;&lt;/P&gt;&lt;/LI&gt;&lt;/UL&gt;&lt;/DIV&gt;&lt;/DIV&gt;</dialogReference></param><param name="Input_land_cover" displayname="Land cover dataset: one file with multiple fields" type="Optional" direction="Input" datatype="Feature Class" expression="{Input_land_cover}"><dialogReference>&lt;DIV STYLE="text-align:Left;"&gt;&lt;DIV&gt;&lt;DIV&gt;&lt;P&gt;&lt;SPAN&gt;If the option &lt;/SPAN&gt;&lt;SPAN STYLE="font-style:italic;"&gt;One shapefile with multiple files &lt;/SPAN&gt;&lt;SPAN&gt;is selected above, specify the path and file&lt;/SPAN&gt;&lt;SPAN&gt;name&lt;/SPAN&gt;&lt;SPAN&gt; of the input land cover dataset here.&lt;/SPAN&gt;&lt;/P&gt;&lt;/DIV&gt;&lt;/DIV&gt;&lt;/DIV&gt;</dialogReference></param><param name="Opening_land_cover" displayname="Land cover dataset: opening land cover shapefile" type="Optional" direction="Input" datatype="Feature Class" expression="{Opening_land_cover}"><dialogReference>&lt;DIV STYLE="text-align:Left;"&gt;&lt;DIV&gt;&lt;DIV&gt;&lt;P&gt;&lt;SPAN&gt;If the option &lt;/SPAN&gt;&lt;SPAN STYLE="font-style:italic;"&gt;Two separate shapefiles &lt;/SPAN&gt;&lt;SPAN&gt;is selected above, specify the path and file&lt;/SPAN&gt;&lt;SPAN&gt;name&lt;/SPAN&gt;&lt;SPAN&gt; of the opening land cover dataset here.&lt;/SPAN&gt;&lt;/P&gt;&lt;/DIV&gt;&lt;/DIV&gt;&lt;/DIV&gt;</dialogReference></param><param name="Closing_land_cover" displayname="Land cover dataset: opening land cover shapefile" type="Optional" direction="Input" datatype="Feature Class" expression="{Closing_land_cover}"><dialogReference>&lt;DIV STYLE="text-align:Left;"&gt;&lt;DIV&gt;&lt;DIV&gt;&lt;P&gt;&lt;SPAN&gt;If the option &lt;/SPAN&gt;&lt;SPAN STYLE="font-style:italic;"&gt;Two separate shapefiles &lt;/SPAN&gt;&lt;SPAN&gt;is selected above, specify the path and file&lt;/SPAN&gt;&lt;SPAN&gt;name&lt;/SPAN&gt;&lt;SPAN&gt; of the closing land cover dataset here.&lt;/SPAN&gt;&lt;/P&gt;&lt;/DIV&gt;&lt;/DIV&gt;&lt;/DIV&gt;</dialogReference></param><param name="Opening_field" displayname="Opening year land cover field" type="Optional" direction="Input" datatype="String" expression="{Opening_field}"><dialogReference>&lt;DIV STYLE="text-align:Left;"&gt;&lt;DIV&gt;&lt;P&gt;&lt;SPAN&gt;Specify the field within the land cover dataset which contains information for opening land cover.&lt;/SPAN&gt;&lt;/P&gt;&lt;/DIV&gt;&lt;/DIV&gt;</dialogReference></param><param name="Closing_field" displayname="Closing year land cover field" type="Optional" direction="Input" datatype="String" expression="{Closing_field}"><dialogReference>&lt;DIV STYLE="text-align:Left;"&gt;&lt;P&gt;&lt;SPAN&gt;Specify the field within the land cover dataset which contains information for closing land cover.&lt;/SPAN&gt;&lt;/P&gt;&lt;/DIV&gt;</dialogReference></param><param name="Land_cover_table" displayname="Land cover label table" type="Optional" direction="Input" datatype="Table" expression="{Land_cover_table}"><dialogReference>&lt;DIV STYLE="text-align:Left;"&gt;&lt;DIV&gt;&lt;P&gt;&lt;SPAN&gt;Specify the path and filename of the table that contains information on the land cover classification code and any other information (e.g. labels) that will be associated with the final output.&lt;/SPAN&gt;&lt;/P&gt;&lt;/DIV&gt;&lt;/DIV&gt;</dialogReference></param><param name="Land_cover_field" displayname="Land cover linking field" type="Optional" direction="Input" datatype="String" expression="{Land_cover_field}"><dialogReference>&lt;DIV STYLE="text-align:Left;"&gt;&lt;DIV&gt;&lt;P&gt;&lt;SPAN&gt;Specify the field within the land cover table above with land cover information that matches the codes used by the input land cover(s).&lt;/SPAN&gt;&lt;/P&gt;&lt;/DIV&gt;&lt;/DIV&gt;</dialogReference></param></parameters><summary>&lt;DIV STYLE="text-align:Left;"&gt;&lt;DIV&gt;&lt;DIV&gt;&lt;P&gt;&lt;SPAN&gt;This tool calculates the land cover extent (square kilometres), absolute change in area, and relative difference in area between land cover extents of two different years.&lt;/SPAN&gt;&lt;SPAN&gt; The land cover classification must use unique identifiers/codes that are the same between the opening and closing land cover timeframes. For example, "10" in the opening land cover may correspond to "agriculture." In the closing land cover, the same code and land cover pairing must be used.&lt;/SPAN&gt;&lt;/P&gt;&lt;P&gt;&lt;SPAN&gt;The outputs produced are a map of the opening land cover showing the areas where there was a negative, positive, or no change in land cover extent, and a csv file summarising the land cover extents, absolute changes, and relative changes.&lt;/SPAN&gt;&lt;/P&gt;&lt;/DIV&gt;&lt;/DIV&gt;&lt;/DIV&gt;</summary></tool><dataIdInfo><idCitation><resTitle>Calculate land cover accounts</resTitle></idCitation><idAbs>&lt;DIV STYLE="text-align:Left;"&gt;&lt;DIV&gt;&lt;DIV&gt;&lt;P&gt;&lt;SPAN&gt;This tool calculates the land cover extent (square kilometres), absolute change in area, and relative difference in area between land cover extents of two different years.&lt;/SPAN&gt;&lt;SPAN&gt; The land cover classification must use unique identifiers/codes that are the same between the opening and closing land cover timeframes. For example, "10" in the opening land cover may correspond to "agriculture." In the closing land cover, the same code and land cover pairing must be used.&lt;/SPAN&gt;&lt;/P&gt;&lt;P&gt;&lt;SPAN&gt;The outputs produced are a map of the opening land cover showing the areas where there was a negative, positive, or no change in land cover extent, and a csv file summarising the land cover extents, absolute changes, and relative changes.&lt;/SPAN&gt;&lt;/P&gt;&lt;/DIV&gt;&lt;/DIV&gt;&lt;/DIV&gt;</idAbs><searchKeys><keyword>LUCI</keyword></searchKeys></dataIdInfo><distInfo><distributor><distorFormat><formatName>ArcToolbox Tool</formatName></distorFormat></distributor></distInfo><mdHrLv><ScopeCd value="005"/></mdHrLv></metadata>
